{"type":"FeatureCollection","features":[{"type":"Feature","properties":{"SeqNo":"175247","Type":"S","DHID":"de:09278:655","Parent":"de:09278:655","Name":"Parkstetten, Schmiedfeld","Latitude":"48,917444","Longitude":"12,612904","MunicipalityCode":"09278170","Municipality":"Parkstetten","DistrictCode":"-","District":"-","Description":"","Authority":"BEG","DelfiName":"-","THID":"D9243E00028F","TariffProvider":"-","LastOperationDate":"2025-12-13T00:00:00","SEV":"nein","geojson_lng":12.612904,"geojson_lat":48.917444},"geometry":{"type":"Point","coordinates":[12.612904,48.917444]}},{"type":"Feature","properties":{"SeqNo":"175248","Type":"Q","DHID":"de:09278:655:0:1","Parent":"de:09278:655","Name":"Parkstetten, Schmiedfeld, Mast 1","Latitude":"48,917444","Longitude":"12,612904","MunicipalityCode":"00000000","Municipality":"-","DistrictCode":"-","District":"-","Description":"Parkstetten, Schmiedfeld, Mast 1","Authority":"BEG","DelfiName":"-","THID":"-","TariffProvider":"-","LastOperationDate":"","SEV":"nein","geojson_lng":12.612904,"geojson_lat":48.917444},"geometry":{"type":"Point","coordinates":[12.612904,48.917444]}},{"type":"Feature","properties":{"SeqNo":"175249","Type":"Q","DHID":"de:09278:655:0:2","Parent":"de:09278:655","Name":"Parkstetten, Schmiedfeld, Mast 2","Latitude":"48,917444","Longitude":"12,612904","MunicipalityCode":"00000000","Municipality":"-","DistrictCode":"-","District":"-","Description":"Parkstetten, Schmiedfeld, Mast 2","Authority":"BEG","DelfiName":"-","THID":"-","TariffProvider":"-","LastOperationDate":"","SEV":"nein","geojson_lng":12.612904,"geojson_lat":48.917444},"geometry":{"type":"Point","coordinates":[12.612904,48.917444]}}]}