{"type":"FeatureCollection","features":[{"type":"Feature","properties":{"SeqNo":"648844","Type":"S","DHID":"de:05754:6626","Parent":"de:05754:6626","Name":"Rb-Hammoor, Siedlung Löhner","Latitude":"51,776538","Longitude":"8,36469","MunicipalityCode":"05754032","Municipality":"Rietberg","DistrictCode":"-","District":"-","Description":"","Authority":"VRR","DelfiName":"-","THID":"D9167A0019E2","TariffProvider":"-","LastOperationDate":"2025-12-12T00:00:00","SEV":"nein","geojson_lng":8.36469,"geojson_lat":51.776538},"geometry":{"type":"Point","coordinates":[8.36469,51.776538]}},{"type":"Feature","properties":{"SeqNo":"648845","Type":"Q","DHID":"de:05754:6626:0:1","Parent":"de:05754:6626","Name":"1","Latitude":"51,776538","Longitude":"8,36469","MunicipalityCode":"00000000","Municipality":"-","DistrictCode":"-","District":"-","Description":"Richtung Großevollmer","Authority":"VRR","DelfiName":"-","THID":"-","TariffProvider":"-","LastOperationDate":"","SEV":"nein","geojson_lng":8.36469,"geojson_lat":51.776538},"geometry":{"type":"Point","coordinates":[8.36469,51.776538]}},{"type":"Feature","properties":{"SeqNo":"648846","Type":"Q","DHID":"de:05754:6626:0:2","Parent":"de:05754:6626","Name":"2","Latitude":"51,776526","Longitude":"8,364663","MunicipalityCode":"00000000","Municipality":"-","DistrictCode":"-","District":"-","Description":"Richtung Ecke Langenberg","Authority":"VRR","DelfiName":"-","THID":"-","TariffProvider":"-","LastOperationDate":"","SEV":"nein","geojson_lng":8.364663,"geojson_lat":51.776526},"geometry":{"type":"Point","coordinates":[8.364663,51.776526]}}]}