{"type":"FeatureCollection","features":[{"type":"Feature","properties":{"SeqNo":"4685","Type":"S","DHID":"de:08115:2212","Parent":"de:08115:2212","Name":"Sindelfingen Feldbergstraße","MunicipalityCode":"08115045","Municipality":"Sindelfingen","DistrictCode":"","District":"","Description":"","Authority":"NVBW","DelfiName":"-","THID":"D91FB30008A4","LastOperationDate":"2025-02-28T00:00:00","SEV":"nein","longitude":"9,008692","latitude":"48,72544","geojson_lng":9.008692,"geojson_lat":48.72544},"geometry":{"type":"Point","coordinates":[9.008692,48.72544]}},{"type":"Feature","properties":{"SeqNo":"4688","Type":"Q","DHID":"de:08115:2212:0:5","Parent":"de:08115:2212","Name":"Bus Rtg ZOB","MunicipalityCode":"00000000","Municipality":"-","DistrictCode":"-","District":"-","Description":"","Authority":"NVBW","DelfiName":"-","THID":"-","LastOperationDate":"","SEV":"nein","longitude":"9,009033","latitude":"48,725321","geojson_lng":9.009033,"geojson_lat":48.725321},"geometry":{"type":"Point","coordinates":[9.009033,48.725321]}},{"type":"Feature","properties":{"SeqNo":"4705","Type":"S","DHID":"de:08115:2219","Parent":"de:08115:2219","Name":"Sifi. Leonberger Str","MunicipalityCode":"08115045","Municipality":"Sindelfingen","DistrictCode":"-","District":"-","Description":"","Authority":"NVBW","DelfiName":"-","THID":"D91FB30008AB","LastOperationDate":"1999-12-31T00:00:00","SEV":"nein","longitude":"9,00959","latitude":"48,72458","geojson_lng":9.00959,"geojson_lat":48.72458},"geometry":{"type":"Point","coordinates":[9.00959,48.72458]}},{"type":"Feature","properties":{"SeqNo":"5707","Type":"S","DHID":"de:08115:4605","Parent":"de:08115:4605","Name":"Sindelf. Eschenried","MunicipalityCode":"08115045","Municipality":"Sindelfingen","DistrictCode":"-","District":"-","Description":"","Authority":"NVBW","DelfiName":"-","THID":"D91FB30011FD","LastOperationDate":"2025-02-28T00:00:00","SEV":"nein","longitude":"9,010542","latitude":"48,725232","geojson_lng":9.010542,"geojson_lat":48.725232},"geometry":{"type":"Point","coordinates":[9.010542,48.725232]}},{"type":"Feature","properties":{"SeqNo":"5708","Type":"A","DHID":"de:08115:4605:1","Parent":"de:08115:4605","Name":"1","MunicipalityCode":"00000000","Municipality":"-","DistrictCode":"-","District":"-","Description":"Bus","Authority":"NVBW","DelfiName":"-","THID":"-","LastOperationDate":"","SEV":"nein","longitude":"9,010542","latitude":"48,72522","geojson_lng":9.010542,"geojson_lat":48.72522},"geometry":{"type":"Point","coordinates":[9.010542,48.72522]}},{"type":"Feature","properties":{"SeqNo":"5709","Type":"Q","DHID":"de:08115:4605:1:3","Parent":"de:08115:4605:1","Name":"3","MunicipalityCode":"00000000","Municipality":"-","DistrictCode":"-","District":"-","Description":"eRtg Friedrich-Ebert-Straße","Authority":"NVBW","DelfiName":"-","THID":"-","LastOperationDate":"","SEV":"nein","longitude":"9,010542","latitude":"48,725232","geojson_lng":9.010542,"geojson_lat":48.725232},"geometry":{"type":"Point","coordinates":[9.010542,48.725232]}},{"type":"Feature","properties":{"SeqNo":"5710","Type":"Q","DHID":"de:08115:4605:1:4","Parent":"de:08115:4605:1","Name":"4","MunicipalityCode":"00000000","Municipality":"-","DistrictCode":"-","District":"-","Description":"eRtg Feldbergstraße","Authority":"NVBW","DelfiName":"-","THID":"-","LastOperationDate":"","SEV":"nein","longitude":"9,010542","latitude":"48,725232","geojson_lng":9.010542,"geojson_lat":48.725232},"geometry":{"type":"Point","coordinates":[9.010542,48.725232]}},{"type":"Feature","properties":{"SeqNo":"5761","Type":"S","DHID":"de:08115:4625","Parent":"de:08115:4625","Name":"Sindelf. Sommerhofenstr.","MunicipalityCode":"08115045","Municipality":"Sindelfingen","DistrictCode":"-","District":"-","Description":"","Authority":"NVBW","DelfiName":"-","THID":"D91FB3001211","LastOperationDate":"2025-02-28T00:00:00","SEV":"nein","longitude":"9,011647","latitude":"48,721321","geojson_lng":9.011647,"geojson_lat":48.721321},"geometry":{"type":"Point","coordinates":[9.011647,48.721321]}},{"type":"Feature","properties":{"SeqNo":"5762","Type":"Q","DHID":"de:08115:4625:0:3","Parent":"de:08115:4625","Name":"3","MunicipalityCode":"00000000","Municipality":"-","DistrictCode":"-","District":"-","Description":"eRtg Pfarrwiesengymnasium","Authority":"NVBW","DelfiName":"-","THID":"-","LastOperationDate":"","SEV":"nein","longitude":"9,011647","latitude":"48,721321","geojson_lng":9.011647,"geojson_lat":48.721321},"geometry":{"type":"Point","coordinates":[9.011647,48.721321]}},{"type":"Feature","properties":{"SeqNo":"5763","Type":"Q","DHID":"de:08115:4625:0:4","Parent":"de:08115:4625","Name":"4","MunicipalityCode":"00000000","Municipality":"-","DistrictCode":"-","District":"-","Description":"eRtg Badezentrum","Authority":"NVBW","DelfiName":"-","THID":"-","LastOperationDate":"","SEV":"nein","longitude":"9,011647","latitude":"48,721321","geojson_lng":9.011647,"geojson_lat":48.721321},"geometry":{"type":"Point","coordinates":[9.011647,48.721321]}},{"type":"Feature","properties":{"SeqNo":"6855","Type":"S","DHID":"de:08115:6757","Parent":"de:08115:6757","Name":"Sindelf. Eschenriedstraße","MunicipalityCode":"08115045","Municipality":"Sindelfingen","DistrictCode":"","District":"","Description":"","Authority":"NVBW","DelfiName":"-","THID":"D91FB3001A65","LastOperationDate":"2025-02-28T00:00:00","SEV":"nein","longitude":"9,014217","latitude":"48,724331","geojson_lng":9.014217,"geojson_lat":48.724331},"geometry":{"type":"Point","coordinates":[9.014217,48.724331]}},{"type":"Feature","properties":{"SeqNo":"6856","Type":"Q","DHID":"de:08115:6757:0:3","Parent":"de:08115:6757","Name":"Rtg Eschenried","MunicipalityCode":"00000000","Municipality":"-","DistrictCode":"-","District":"-","Description":"","Authority":"NVBW","DelfiName":"-","THID":"-","LastOperationDate":"","SEV":"nein","longitude":"9,014163","latitude":"48,724314","geojson_lng":9.014163,"geojson_lat":48.724314},"geometry":{"type":"Point","coordinates":[9.014163,48.724314]}}]}