{"type":"FeatureCollection","features":[{"type":"Feature","properties":{"SeqNo":"144127","Type":"S","DHID":"de:09189:66354","Parent":"de:09189:66354","Name":"Blindau","MunicipalityCode":"09189139","Municipality":"Reit im Winkl","DistrictCode":"-","District":"-","Description":"","Authority":"BEG","DelfiName":"-","THID":"D923E5010332","LastOperationDate":"2025-02-28T00:00:00","SEV":"nein","longitude":"12,476387","latitude":"47,662927","geojson_lng":12.476387,"geojson_lat":47.662927},"geometry":{"type":"Point","coordinates":[12.476387,47.662927]}},{"type":"Feature","properties":{"SeqNo":"144128","Type":"Q","DHID":"de:09189:66354:0:1","Parent":"de:09189:66354","Name":"Blindau, Mast 1","MunicipalityCode":"00000000","Municipality":"-","DistrictCode":"-","District":"-","Description":"Blindau, Mast 1","Authority":"BEG","DelfiName":"-","THID":"-","LastOperationDate":"","SEV":"nein","longitude":"12,476396","latitude":"47,662933","geojson_lng":12.476396,"geojson_lat":47.662933},"geometry":{"type":"Point","coordinates":[12.476396,47.662933]}},{"type":"Feature","properties":{"SeqNo":"144129","Type":"Q","DHID":"de:09189:66354:0:2","Parent":"de:09189:66354","Name":"Blindau, Mast 2","MunicipalityCode":"00000000","Municipality":"-","DistrictCode":"-","District":"-","Description":"Blindau, Mast 2","Authority":"BEG","DelfiName":"-","THID":"-","LastOperationDate":"","SEV":"nein","longitude":"12,476369","latitude":"47,662915","geojson_lng":12.476369,"geojson_lat":47.662915},"geometry":{"type":"Point","coordinates":[12.476369,47.662915]}},{"type":"Feature","properties":{"SeqNo":"144130","Type":"S","DHID":"de:09189:66355","Parent":"de:09189:66355","Name":"Benz-Eck-Lifte","MunicipalityCode":"09189139","Municipality":"Reit im Winkl","DistrictCode":"-","District":"-","Description":"","Authority":"BEG","DelfiName":"-","THID":"D923E5010333","LastOperationDate":"2025-02-28T00:00:00","SEV":"nein","longitude":"12,472335","latitude":"47,663351","geojson_lng":12.472335,"geojson_lat":47.663351},"geometry":{"type":"Point","coordinates":[12.472335,47.663351]}},{"type":"Feature","properties":{"SeqNo":"144131","Type":"Q","DHID":"de:09189:66355:0:1","Parent":"de:09189:66355","Name":"Benz-Eck-Lifte, Mast 1","MunicipalityCode":"00000000","Municipality":"-","DistrictCode":"-","District":"-","Description":"Benz-Eck-Lifte, Mast 1","Authority":"BEG","DelfiName":"-","THID":"-","LastOperationDate":"","SEV":"nein","longitude":"12,472344","latitude":"47,663351","geojson_lng":12.472344,"geojson_lat":47.663351},"geometry":{"type":"Point","coordinates":[12.472344,47.663351]}},{"type":"Feature","properties":{"SeqNo":"144132","Type":"Q","DHID":"de:09189:66355:0:2","Parent":"de:09189:66355","Name":"Benz-Eck-Lifte, Mast 1","MunicipalityCode":"00000000","Municipality":"-","DistrictCode":"-","District":"-","Description":"Benz-Eck-Lifte, Mast 1","Authority":"BEG","DelfiName":"-","THID":"-","LastOperationDate":"","SEV":"nein","longitude":"12,472335","latitude":"47,663351","geojson_lng":12.472335,"geojson_lat":47.663351},"geometry":{"type":"Point","coordinates":[12.472335,47.663351]}}]}