{"type":"FeatureCollection","features":[{"type":"Feature","properties":{"SeqNo":"50854","Type":"S","DHID":"de:08236:3018","Parent":"de:08236:3018","Name":"Mühlacker Betriebshof Engel","MunicipalityCode":"08236040","Municipality":"Mühlacker","DistrictCode":"-","District":"-","Description":"","Authority":"NVBW","DelfiName":"-","THID":"D9202C000BCA","LastOperationDate":"2025-06-13T00:00:00","SEV":"nein","longitude":"8,869049","latitude":"48,955783","geojson_lng":8.869049,"geojson_lat":48.955783},"geometry":{"type":"Point","coordinates":[8.869049,48.955783]}},{"type":"Feature","properties":{"SeqNo":"50855","Type":"Q","DHID":"de:08236:3018:0:1","Parent":"de:08236:3018","Name":"1","MunicipalityCode":"00000000","Municipality":"-","DistrictCode":"-","District":"-","Description":"Richtung Industriegebiet","Authority":"NVBW","DelfiName":"-","THID":"-","LastOperationDate":"","SEV":"nein","longitude":"8,868995","latitude":"48,955747","geojson_lng":8.868995,"geojson_lat":48.955747},"geometry":{"type":"Point","coordinates":[8.868995,48.955747]}},{"type":"Feature","properties":{"SeqNo":"50856","Type":"Q","DHID":"de:08236:3018:0:2","Parent":"de:08236:3018","Name":"2","MunicipalityCode":"00000000","Municipality":"-","DistrictCode":"-","District":"-","Description":"Richtung Busbahnhof","Authority":"NVBW","DelfiName":"-","THID":"-","LastOperationDate":"","SEV":"nein","longitude":"8,869049","latitude":"48,955783","geojson_lng":8.869049,"geojson_lat":48.955783},"geometry":{"type":"Point","coordinates":[8.869049,48.955783]}}]}