{"type":"FeatureCollection","features":[{"type":"Feature","properties":{"SeqNo":"175199","Type":"S","DHID":"de:09371:19202","Parent":"de:09371:19202","Name":"Schnaittenbach Am Festplatz","MunicipalityCode":"09371150","Municipality":"Schnaittenbach","DistrictCode":"","District":"","Description":"","Authority":"BEG","DelfiName":"-","THID":"D9249B004B02","LastOperationDate":"2025-06-14T00:00:00","SEV":"nein","longitude":"12,013116","latitude":"49,549811","geojson_lng":12.013116,"geojson_lat":49.549811},"geometry":{"type":"Point","coordinates":[12.013116,49.549811]}},{"type":"Feature","properties":{"SeqNo":"175200","Type":"Q","DHID":"de:09371:19202:0:1","Parent":"de:09371:19202","Name":"1","MunicipalityCode":"00000000","Municipality":"-","DistrictCode":"-","District":"-","Description":"","Authority":"BEG","DelfiName":"-","THID":"-","LastOperationDate":"","SEV":"nein","longitude":"12,013018","latitude":"49,549525","geojson_lng":12.013018,"geojson_lat":49.549525},"geometry":{"type":"Point","coordinates":[12.013018,49.549525]}},{"type":"Feature","properties":{"SeqNo":"175201","Type":"Q","DHID":"de:09371:19202:0:2","Parent":"de:09371:19202","Name":"2","MunicipalityCode":"00000000","Municipality":"-","DistrictCode":"-","District":"-","Description":"","Authority":"BEG","DelfiName":"-","THID":"-","LastOperationDate":"","SEV":"nein","longitude":"12,012991","latitude":"49,550056","geojson_lng":12.012991,"geojson_lat":49.550056},"geometry":{"type":"Point","coordinates":[12.012991,49.550056]}},{"type":"Feature","properties":{"SeqNo":"175202","Type":"S","DHID":"de:09371:19203","Parent":"de:09371:19203","Name":"Schnaittenbach Nettomarkt","MunicipalityCode":"09371150","Municipality":"Schnaittenbach","DistrictCode":"","District":"","Description":"","Authority":"BEG","DelfiName":"-","THID":"D9249B004B03","LastOperationDate":"2025-06-14T00:00:00","SEV":"nein","longitude":"12,010808","latitude":"49,549758","geojson_lng":12.010808,"geojson_lat":49.549758},"geometry":{"type":"Point","coordinates":[12.010808,49.549758]}},{"type":"Feature","properties":{"SeqNo":"175203","Type":"Q","DHID":"de:09371:19203:0:1","Parent":"de:09371:19203","Name":"1","MunicipalityCode":"00000000","Municipality":"-","DistrictCode":"-","District":"-","Description":"","Authority":"BEG","DelfiName":"-","THID":"-","LastOperationDate":"","SEV":"nein","longitude":"12,010439","latitude":"49,549805","geojson_lng":12.010439,"geojson_lat":49.549805},"geometry":{"type":"Point","coordinates":[12.010439,49.549805]}},{"type":"Feature","properties":{"SeqNo":"175204","Type":"Q","DHID":"de:09371:19203:0:2","Parent":"de:09371:19203","Name":"2","MunicipalityCode":"00000000","Municipality":"-","DistrictCode":"-","District":"-","Description":"","Authority":"BEG","DelfiName":"-","THID":"-","LastOperationDate":"","SEV":"nein","longitude":"12,011077","latitude":"49,549706","geojson_lng":12.011077,"geojson_lat":49.549706},"geometry":{"type":"Point","coordinates":[12.011077,49.549706]}}]}