{"type":"FeatureCollection","features":[{"type":"Feature","properties":{"SeqNo":"892241","Type":"S","DHID":"de:06635:205589","Parent":"de:06635:205589","Name":"Twistetal-Ober-Waroldern Mitte","MunicipalityCode":"06635018","Municipality":"Twistetal","DistrictCode":"","District":"","Description":"","Authority":"NVV","DelfiName":"-","THID":"D919EB032315","LastOperationDate":"2025-06-13T00:00:00","SEV":"nein","longitude":"8,968569","latitude":"51,303631","geojson_lng":8.968569,"geojson_lat":51.303631},"geometry":{"type":"Point","coordinates":[8.968569,51.303631]}},{"type":"Feature","properties":{"SeqNo":"892242","Type":"Q","DHID":"de:06635:205589::A","Parent":"de:06635:205589","Name":"Twistetal-Ober-Waroldern Mitte, Steig A","MunicipalityCode":"00000000","Municipality":"-","DistrictCode":"-","District":"-","Description":"","Authority":"NVV","DelfiName":"-","THID":"-","LastOperationDate":"","SEV":"nein","longitude":"8,96987","latitude":"51,30403","geojson_lng":8.96987,"geojson_lat":51.30403},"geometry":{"type":"Point","coordinates":[8.96987,51.30403]}},{"type":"Feature","properties":{"SeqNo":"892243","Type":"Q","DHID":"de:06635:205589::AST","Parent":"de:06635:205589","Name":"Twistetal-Ober-Waroldern Mitte, AST","MunicipalityCode":"00000000","Municipality":"-","DistrictCode":"-","District":"-","Description":"","Authority":"NVV","DelfiName":"-","THID":"-","LastOperationDate":"","SEV":"nein","longitude":"8,968569","latitude":"51,303631","geojson_lng":8.968569,"geojson_lat":51.303631},"geometry":{"type":"Point","coordinates":[8.968569,51.303631]}},{"type":"Feature","properties":{"SeqNo":"892244","Type":"Q","DHID":"de:06635:205589::B","Parent":"de:06635:205589","Name":"Twistetal-Ober-Waroldern Mitte, Steig B","MunicipalityCode":"00000000","Municipality":"-","DistrictCode":"-","District":"-","Description":"","Authority":"NVV","DelfiName":"-","THID":"-","LastOperationDate":"","SEV":"nein","longitude":"8,96758","latitude":"51,30356","geojson_lng":8.96758,"geojson_lat":51.30356},"geometry":{"type":"Point","coordinates":[8.96758,51.30356]}}]}