{"type":"FeatureCollection","features":[{"type":"Feature","properties":{"SeqNo":"24196","Type":"S","DHID":"de:08125:688","Parent":"de:08125:688","Name":"Leingarten Siedlung","MunicipalityCode":"08125058","Municipality":"Leingarten","DistrictCode":"","District":"","Description":"","Authority":"NVBW","DelfiName":"-","THID":"D91FBD0002B0","LastOperationDate":"1999-12-31T00:00:00","SEV":"nein","longitude":"9,0967","latitude":"49,145947","geojson_lng":9.0967,"geojson_lat":49.145947},"geometry":{"type":"Point","coordinates":[9.0967,49.145947]}}]}