{"type":"FeatureCollection","features":[{"type":"Feature","properties":{"SeqNo":"397339","Type":"S","DHID":"de:04011:14163","Parent":"de:04011:14163","Name":"Bremen Rönnebecker Straße","Latitude":"53,185739","Longitude":"8,555946","MunicipalityCode":"04011000","Municipality":"Bremen","DistrictCode":"","District":"","Description":"","Authority":"VBN","DelfiName":"-","THID":"D90FAB003753","TariffProvider":"-","LastOperationDate":"2025-10-05T00:00:00","SEV":"nein","geojson_lng":8.555946,"geojson_lat":53.185739},"geometry":{"type":"Point","coordinates":[8.555946,53.185739]}},{"type":"Feature","properties":{"SeqNo":"397340","Type":"Q","DHID":"de:04011:14163::1","Parent":"de:04011:14163","Name":"Bremen Rönnebecker Straße","Latitude":"53,186159","Longitude":"8,555164","MunicipalityCode":"00000000","Municipality":"-","DistrictCode":"-","District":"-","Description":"","Authority":"VBN","DelfiName":"-","THID":"-","TariffProvider":"-","LastOperationDate":"","SEV":"nein","geojson_lng":8.555164,"geojson_lat":53.186159},"geometry":{"type":"Point","coordinates":[8.555164,53.186159]}},{"type":"Feature","properties":{"SeqNo":"397341","Type":"Q","DHID":"de:04011:14163::2","Parent":"de:04011:14163","Name":"Bremen Rönnebecker Straße","Latitude":"53,184869","Longitude":"8,556314","MunicipalityCode":"00000000","Municipality":"-","DistrictCode":"-","District":"-","Description":"","Authority":"VBN","DelfiName":"-","THID":"-","TariffProvider":"-","LastOperationDate":"","SEV":"nein","geojson_lng":8.556314,"geojson_lat":53.184869},"geometry":{"type":"Point","coordinates":[8.556314,53.184869]}},{"type":"Feature","properties":{"SeqNo":"397342","Type":"Q","DHID":"de:04011:14163::3","Parent":"de:04011:14163","Name":"Bremen Rönnebecker Straße","Latitude":"53,18619","Longitude":"8,55636","MunicipalityCode":"00000000","Municipality":"-","DistrictCode":"-","District":"-","Description":"","Authority":"VBN","DelfiName":"-","THID":"-","TariffProvider":"-","LastOperationDate":"","SEV":"nein","geojson_lng":8.55636,"geojson_lat":53.18619},"geometry":{"type":"Point","coordinates":[8.55636,53.18619]}}]}