{"type":"FeatureCollection","features":[{"type":"Feature","properties":{"SeqNo":"887478","Type":"S","DHID":"de:06633:203829","Parent":"de:06633:203829","Name":"Vellmar-Obervellmar Schöne Aussicht","MunicipalityCode":"06633026","Municipality":"Vellmar","DistrictCode":"","District":"","Description":"","Authority":"NVV","DelfiName":"-","THID":"D919E9031C35","LastOperationDate":"2025-06-14T00:00:00","SEV":"nein","longitude":"9,447415","latitude":"51,357958","geojson_lng":9.447415,"geojson_lat":51.357958},"geometry":{"type":"Point","coordinates":[9.447415,51.357958]}},{"type":"Feature","properties":{"SeqNo":"887480","Type":"Q","DHID":"de:06633:203829::AST","Parent":"de:06633:203829","Name":"Vellmar-Obervellmar Schöne Aussicht, AST","MunicipalityCode":"00000000","Municipality":"-","DistrictCode":"-","District":"-","Description":"","Authority":"NVV","DelfiName":"-","THID":"-","LastOperationDate":"","SEV":"nein","longitude":"9,447415","latitude":"51,357958","geojson_lng":9.447415,"geojson_lat":51.357958},"geometry":{"type":"Point","coordinates":[9.447415,51.357958]}},{"type":"Feature","properties":{"SeqNo":"887486","Type":"S","DHID":"de:06633:203831","Parent":"de:06633:203831","Name":"Vellmar-Obervellmar Habichtswalder Straße","MunicipalityCode":"06633026","Municipality":"Vellmar","DistrictCode":"","District":"","Description":"","Authority":"NVV","DelfiName":"-","THID":"D919E9031C37","LastOperationDate":"2025-06-14T00:00:00","SEV":"nein","longitude":"9,448207","latitude":"51,359771","geojson_lng":9.448207,"geojson_lat":51.359771},"geometry":{"type":"Point","coordinates":[9.448207,51.359771]}},{"type":"Feature","properties":{"SeqNo":"887487","Type":"Q","DHID":"de:06633:203831::A","Parent":"de:06633:203831","Name":"Vellmar-Obervellmar Habichtswalder Straße, Steig A","MunicipalityCode":"00000000","Municipality":"-","DistrictCode":"-","District":"-","Description":"","Authority":"NVV","DelfiName":"-","THID":"-","LastOperationDate":"","SEV":"nein","longitude":"9,444428","latitude":"51,358532","geojson_lng":9.444428,"geojson_lat":51.358532},"geometry":{"type":"Point","coordinates":[9.444428,51.358532]}},{"type":"Feature","properties":{"SeqNo":"887488","Type":"Q","DHID":"de:06633:203831::AST","Parent":"de:06633:203831","Name":"Vellmar-Obervellmar Habichtswalder Straße, AST","MunicipalityCode":"00000000","Municipality":"-","DistrictCode":"-","District":"-","Description":"","Authority":"NVV","DelfiName":"-","THID":"-","LastOperationDate":"","SEV":"nein","longitude":"9,448207","latitude":"51,359771","geojson_lng":9.448207,"geojson_lat":51.359771},"geometry":{"type":"Point","coordinates":[9.448207,51.359771]}},{"type":"Feature","properties":{"SeqNo":"887489","Type":"Q","DHID":"de:06633:203831::B","Parent":"de:06633:203831","Name":"Vellmar-Obervellmar Habichtswalder Straße, Steig B","MunicipalityCode":"00000000","Municipality":"-","DistrictCode":"-","District":"-","Description":"","Authority":"NVV","DelfiName":"-","THID":"-","LastOperationDate":"","SEV":"nein","longitude":"9,444049","latitude":"51,358457","geojson_lng":9.444049,"geojson_lat":51.358457},"geometry":{"type":"Point","coordinates":[9.444049,51.358457]}}]}