{"type":"FeatureCollection","features":[{"type":"Feature","properties":{"highway":"bus_stop","public_transport":"platform","name":"RK Kerk","ref:IFOPT":"NL:Q:59632220","_quaycode":"NL:Q:59632220","_town":"Meije","_status":"available","_mode":"bus","_direction":8,"_visuallyAccessible":false,"_disabledAccessible":false,"geojson_lng":4.792444360545063,"geojson_lat":52.12176571688663},"geometry":{"type":"Point","coordinates":[4.792444360545063,52.12176571688663]}},{"type":"Feature","properties":{"highway":"bus_stop","public_transport":"platform","name":"RK Kerk","ref:IFOPT":"NL:Q:59632000","_quaycode":"NL:Q:59632000","_town":"Meije","_status":"available","_mode":"bus","_direction":180,"_visuallyAccessible":false,"_disabledAccessible":false,"geojson_lng":4.792269387731774,"geojson_lat":52.121746857919405},"geometry":{"type":"Point","coordinates":[4.792269387731774,52.121746857919405]}}]}