{"type":"FeatureCollection","features":[{"type":"Feature","properties":{"SeqNo":"770303","Type":"S","DHID":"de:07337:40001","Parent":"de:07337:40001","Name":"Offenbach, Turn- und Festhalle","MunicipalityCode":"07337061","Municipality":"Offenbach an der Queich","DistrictCode":"","District":"","Description":"","Authority":"VRN","DelfiName":"-","THID":"D91CA9009C41","LastOperationDate":"2025-06-14T00:00:00","SEV":"nein","longitude":"8,189985","latitude":"49,199051","geojson_lng":8.189985,"geojson_lat":49.199051},"geometry":{"type":"Point","coordinates":[8.189985,49.199051]}},{"type":"Feature","properties":{"SeqNo":"770304","Type":"Q","DHID":"de:07337:40001:0:RiN","Parent":"de:07337:40001","Name":"RiN Mörlheim/Essingen","MunicipalityCode":"00000000","Municipality":"-","DistrictCode":"-","District":"-","Description":"","Authority":"VRN","DelfiName":"-","THID":"-","LastOperationDate":"","SEV":"nein","longitude":"8,190048","latitude":"49,19901","geojson_lng":8.190048,"geojson_lat":49.19901},"geometry":{"type":"Point","coordinates":[8.190048,49.19901]}},{"type":"Feature","properties":{"SeqNo":"770305","Type":"Q","DHID":"de:07337:40001:0:RiS","Parent":"de:07337:40001","Name":"RiS Mozartstraße","MunicipalityCode":"00000000","Municipality":"-","DistrictCode":"-","District":"-","Description":"","Authority":"VRN","DelfiName":"-","THID":"-","LastOperationDate":"","SEV":"nein","longitude":"8,189905","latitude":"49,199063","geojson_lng":8.189905,"geojson_lat":49.199063},"geometry":{"type":"Point","coordinates":[8.189905,49.199063]}}]}