{"type":"FeatureCollection","features":[{"type":"Feature","properties":{"SeqNo":"439147","Type":"S","DHID":"de:06433:14253","Parent":"de:06433:14253","Name":"Raunheim Am Prime-Parc","Latitude":"50,015274","Longitude":"8,460044","MunicipalityCode":"06433010","Municipality":"Raunheim","DistrictCode":"-","District":"-","Description":"","Authority":"rms","DelfiName":"-","THID":"D919210037AD","TariffProvider":"-","LastOperationDate":"2025-12-13T00:00:00","SEV":"nein","geojson_lng":8.460044,"geojson_lat":50.015274},"geometry":{"type":"Point","coordinates":[8.460044,50.015274]}},{"type":"Feature","properties":{"SeqNo":"439148","Type":"A","DHID":"de:06433:14253:1","Parent":"de:06433:14253","Name":"Raunheim Am Prime-Parc | NRüsselsheim","Latitude":"50,015318","Longitude":"8,459778","MunicipalityCode":"00000000","Municipality":"-","DistrictCode":"-","District":"-","Description":"","Authority":"rms","DelfiName":"-","THID":"-","TariffProvider":"-","LastOperationDate":"","SEV":"nein","geojson_lng":8.459778,"geojson_lat":50.015318},"geometry":{"type":"Point","coordinates":[8.459778,50.015318]}},{"type":"Feature","properties":{"SeqNo":"439149","Type":"A","DHID":"de:06433:14253:2","Parent":"de:06433:14253","Name":"Raunheim Am Prime-Parc | NKelsterbach","Latitude":"50,015212","Longitude":"8,46017","MunicipalityCode":"00000000","Municipality":"-","DistrictCode":"-","District":"-","Description":"","Authority":"rms","DelfiName":"-","THID":"-","TariffProvider":"-","LastOperationDate":"","SEV":"nein","geojson_lng":8.46017,"geojson_lat":50.015212},"geometry":{"type":"Point","coordinates":[8.46017,50.015212]}},{"type":"Feature","properties":{"SeqNo":"439150","Type":"Q","DHID":"de:06433:14253:1:1","Parent":"de:06433:14253:1","Name":"Raunheim Am Prime-Parc | NRüsselsheim | NRüsselsheim","Latitude":"50,015318","Longitude":"8,459778","MunicipalityCode":"00000000","Municipality":"-","DistrictCode":"-","District":"-","Description":"","Authority":"rms","DelfiName":"-","THID":"-","TariffProvider":"-","LastOperationDate":"","SEV":"nein","geojson_lng":8.459778,"geojson_lat":50.015318},"geometry":{"type":"Point","coordinates":[8.459778,50.015318]}},{"type":"Feature","properties":{"SeqNo":"439151","Type":"Q","DHID":"de:06433:14253:2:2","Parent":"de:06433:14253:2","Name":"Raunheim Am Prime-Parc | NKelsterbach | NKelsterbach","Latitude":"50,015212","Longitude":"8,46017","MunicipalityCode":"00000000","Municipality":"-","DistrictCode":"-","District":"-","Description":"","Authority":"rms","DelfiName":"-","THID":"-","TariffProvider":"-","LastOperationDate":"","SEV":"nein","geojson_lng":8.46017,"geojson_lat":50.015212},"geometry":{"type":"Point","coordinates":[8.46017,50.015212]}},{"type":"Feature","properties":{"SeqNo":"439571","Type":"S","DHID":"de:06433:14351","Parent":"de:06433:14351","Name":"Raunheim Airgate One","Latitude":"50,020501","Longitude":"8,466572","MunicipalityCode":"06433010","Municipality":"Raunheim","DistrictCode":"-","District":"-","Description":"","Authority":"rms","DelfiName":"-","THID":"D9192100380F","TariffProvider":"-","LastOperationDate":"1999-12-31T00:00:00","SEV":"nein","geojson_lng":8.466572,"geojson_lat":50.020501},"geometry":{"type":"Point","coordinates":[8.466572,50.020501]}},{"type":"Feature","properties":{"SeqNo":"439572","Type":"A","DHID":"de:06433:14351:1","Parent":"de:06433:14351","Name":"Raunheim Airgate One | VNRüsselsheim","Latitude":"50,020501","Longitude":"8,466572","MunicipalityCode":"00000000","Municipality":"-","DistrictCode":"-","District":"-","Description":"","Authority":"rms","DelfiName":"-","THID":"-","TariffProvider":"-","LastOperationDate":"","SEV":"nein","geojson_lng":8.466572,"geojson_lat":50.020501},"geometry":{"type":"Point","coordinates":[8.466572,50.020501]}},{"type":"Feature","properties":{"SeqNo":"439573","Type":"Q","DHID":"de:06433:14351:1:1","Parent":"de:06433:14351:1","Name":"Raunheim Airgate One | VNRüsselsheim | VNRüsselsheim","Latitude":"50,020501","Longitude":"8,466572","MunicipalityCode":"00000000","Municipality":"-","DistrictCode":"-","District":"-","Description":"","Authority":"rms","DelfiName":"-","THID":"-","TariffProvider":"-","LastOperationDate":"","SEV":"nein","geojson_lng":8.466572,"geojson_lat":50.020501},"geometry":{"type":"Point","coordinates":[8.466572,50.020501]}},{"type":"Feature","properties":{"SeqNo":"439574","Type":"S","DHID":"de:06433:14352","Parent":"de:06433:14352","Name":"Raunheim Magellan-Allee","Latitude":"50,015374","Longitude":"8,466001","MunicipalityCode":"06433010","Municipality":"Raunheim","DistrictCode":"-","District":"-","Description":"","Authority":"rms","DelfiName":"-","THID":"D91921003810","TariffProvider":"-","LastOperationDate":"2025-12-12T00:00:00","SEV":"nein","geojson_lng":8.466001,"geojson_lat":50.015374},"geometry":{"type":"Point","coordinates":[8.466001,50.015374]}},{"type":"Feature","properties":{"SeqNo":"439575","Type":"A","DHID":"de:06433:14352:1","Parent":"de:06433:14352","Name":"Raunheim Magellan-Allee | VBahnhof","Latitude":"50,015528","Longitude":"8,46632","MunicipalityCode":"00000000","Municipality":"-","DistrictCode":"-","District":"-","Description":"","Authority":"rms","DelfiName":"-","THID":"-","TariffProvider":"-","LastOperationDate":"","SEV":"nein","geojson_lng":8.46632,"geojson_lat":50.015528},"geometry":{"type":"Point","coordinates":[8.46632,50.015528]}},{"type":"Feature","properties":{"SeqNo":"439576","Type":"A","DHID":"de:06433:14352:2","Parent":"de:06433:14352","Name":"Raunheim Magellan-Allee | NBahnhof","Latitude":"50,01521","Longitude":"8,465668","MunicipalityCode":"00000000","Municipality":"-","DistrictCode":"-","District":"-","Description":"","Authority":"rms","DelfiName":"-","THID":"-","TariffProvider":"-","LastOperationDate":"","SEV":"nein","geojson_lng":8.465668,"geojson_lat":50.01521},"geometry":{"type":"Point","coordinates":[8.465668,50.01521]}},{"type":"Feature","properties":{"SeqNo":"439577","Type":"Q","DHID":"de:06433:14352:1:1","Parent":"de:06433:14352:1","Name":"Raunheim Magellan-Allee | VBahnhof | VBahnhof","Latitude":"50,015528","Longitude":"8,46632","MunicipalityCode":"00000000","Municipality":"-","DistrictCode":"-","District":"-","Description":"","Authority":"rms","DelfiName":"-","THID":"-","TariffProvider":"-","LastOperationDate":"","SEV":"nein","geojson_lng":8.46632,"geojson_lat":50.015528},"geometry":{"type":"Point","coordinates":[8.46632,50.015528]}},{"type":"Feature","properties":{"SeqNo":"439578","Type":"Q","DHID":"de:06433:14352:2:2","Parent":"de:06433:14352:2","Name":"Raunheim Magellan-Allee | NBahnhof | NBahnhof","Latitude":"50,01521","Longitude":"8,465668","MunicipalityCode":"00000000","Municipality":"-","DistrictCode":"-","District":"-","Description":"","Authority":"rms","DelfiName":"-","THID":"-","TariffProvider":"-","LastOperationDate":"","SEV":"nein","geojson_lng":8.465668,"geojson_lat":50.01521},"geometry":{"type":"Point","coordinates":[8.465668,50.01521]}},{"type":"Feature","properties":{"SeqNo":"439659","Type":"S","DHID":"de:06433:14371","Parent":"de:06433:14371","Name":"Raunheim Rudolf-Ihm-Platz","Latitude":"50,014778","Longitude":"8,461529","MunicipalityCode":"06433010","Municipality":"Raunheim","DistrictCode":"","District":"","Description":"","Authority":"rms","DelfiName":"-","THID":"D91921003823","TariffProvider":"-","LastOperationDate":"2025-12-13T00:00:00","SEV":"nein","geojson_lng":8.461529,"geojson_lat":50.014778},"geometry":{"type":"Point","coordinates":[8.461529,50.014778]}},{"type":"Feature","properties":{"SeqNo":"439660","Type":"A","DHID":"de:06433:14371:1","Parent":"de:06433:14371","Name":"Raunheim Rudolf-Ihm-Platz | VKelsterbach","Latitude":"50,014696","Longitude":"8,461488","MunicipalityCode":"00000000","Municipality":"-","DistrictCode":"-","District":"-","Description":"","Authority":"rms","DelfiName":"-","THID":"-","TariffProvider":"-","LastOperationDate":"","SEV":"nein","geojson_lng":8.461488,"geojson_lat":50.014696},"geometry":{"type":"Point","coordinates":[8.461488,50.014696]}},{"type":"Feature","properties":{"SeqNo":"439661","Type":"A","DHID":"de:06433:14371:2","Parent":"de:06433:14371","Name":"Raunheim Rudolf-Ihm-Platz | NKelsterbach","Latitude":"50,014859","Longitude":"8,461597","MunicipalityCode":"00000000","Municipality":"-","DistrictCode":"-","District":"-","Description":"","Authority":"rms","DelfiName":"-","THID":"-","TariffProvider":"-","LastOperationDate":"","SEV":"nein","geojson_lng":8.461597,"geojson_lat":50.014859},"geometry":{"type":"Point","coordinates":[8.461597,50.014859]}},{"type":"Feature","properties":{"SeqNo":"439662","Type":"Q","DHID":"de:06433:14371:1:1","Parent":"de:06433:14371:1","Name":"Raunheim Rudolf-Ihm-Platz | VKelsterbach | VKelsterbach","Latitude":"50,014696","Longitude":"8,461488","MunicipalityCode":"00000000","Municipality":"-","DistrictCode":"-","District":"-","Description":"","Authority":"rms","DelfiName":"-","THID":"-","TariffProvider":"-","LastOperationDate":"","SEV":"nein","geojson_lng":8.461488,"geojson_lat":50.014696},"geometry":{"type":"Point","coordinates":[8.461488,50.014696]}},{"type":"Feature","properties":{"SeqNo":"439663","Type":"Q","DHID":"de:06433:14371:2:2","Parent":"de:06433:14371:2","Name":"Raunheim Rudolf-Ihm-Platz | NKelsterbach | NKelsterbach","Latitude":"50,014859","Longitude":"8,461597","MunicipalityCode":"00000000","Municipality":"-","DistrictCode":"-","District":"-","Description":"","Authority":"rms","DelfiName":"-","THID":"-","TariffProvider":"-","LastOperationDate":"","SEV":"nein","geojson_lng":8.461597,"geojson_lat":50.014859},"geometry":{"type":"Point","coordinates":[8.461597,50.014859]}},{"type":"Feature","properties":{"SeqNo":"440357","Type":"S","DHID":"de:06433:4901","Parent":"de:06433:4901","Name":"Raunheim Christoph-Probst-Kreisel","Latitude":"50,016997","Longitude":"8,465215","MunicipalityCode":"06433010","Municipality":"Raunheim","DistrictCode":"","District":"","Description":"","Authority":"rms","DelfiName":"-","THID":"D91921001325","TariffProvider":"-","LastOperationDate":"2025-12-13T00:00:00","SEV":"nein","geojson_lng":8.465215,"geojson_lat":50.016997},"geometry":{"type":"Point","coordinates":[8.465215,50.016997]}},{"type":"Feature","properties":{"SeqNo":"440358","Type":"A","DHID":"de:06433:4901:1","Parent":"de:06433:4901","Name":"Raunheim Christoph-Probst-Kreisel | NRüsselsheim","Latitude":"50,016997","Longitude":"8,465159","MunicipalityCode":"00000000","Municipality":"-","DistrictCode":"-","District":"-","Description":"","Authority":"rms","DelfiName":"-","THID":"-","TariffProvider":"-","LastOperationDate":"","SEV":"nein","geojson_lng":8.465159,"geojson_lat":50.016997},"geometry":{"type":"Point","coordinates":[8.465159,50.016997]}},{"type":"Feature","properties":{"SeqNo":"440359","Type":"A","DHID":"de:06433:4901:2","Parent":"de:06433:4901","Name":"Raunheim Christoph-Probst-Kreisel | NKelsterbach","Latitude":"50,016971","Longitude":"8,465327","MunicipalityCode":"00000000","Municipality":"-","DistrictCode":"-","District":"-","Description":"","Authority":"rms","DelfiName":"-","THID":"-","TariffProvider":"-","LastOperationDate":"","SEV":"nein","geojson_lng":8.465327,"geojson_lat":50.016971},"geometry":{"type":"Point","coordinates":[8.465327,50.016971]}},{"type":"Feature","properties":{"SeqNo":"440360","Type":"Q","DHID":"de:06433:4901:1:1","Parent":"de:06433:4901:1","Name":"Raunheim Chr.-Probst-Kreisel | NRüsselsheim | NRüsselsheim","Latitude":"50,016997","Longitude":"8,465159","MunicipalityCode":"00000000","Municipality":"-","DistrictCode":"-","District":"-","Description":"","Authority":"rms","DelfiName":"-","THID":"-","TariffProvider":"-","LastOperationDate":"","SEV":"nein","geojson_lng":8.465159,"geojson_lat":50.016997},"geometry":{"type":"Point","coordinates":[8.465159,50.016997]}},{"type":"Feature","properties":{"SeqNo":"440361","Type":"Q","DHID":"de:06433:4901:2:2","Parent":"de:06433:4901:2","Name":"Raunheim Chr.-Probst-Kreisel | NKelsterbach | NKelsterbach","Latitude":"50,016971","Longitude":"8,465327","MunicipalityCode":"00000000","Municipality":"-","DistrictCode":"-","District":"-","Description":"","Authority":"rms","DelfiName":"-","THID":"-","TariffProvider":"-","LastOperationDate":"","SEV":"nein","geojson_lng":8.465327,"geojson_lat":50.016971},"geometry":{"type":"Point","coordinates":[8.465327,50.016971]}}]}